sip_python/__init__.py
sip_python/helpers.py
sip_python/py.typed
sip_python/sip_python_ext.abi3.so
sip_python/sip_python_ext.pyi
sip_python-0.0.2.dist-info/METADATA
sip_python-0.0.2.dist-info/WHEEL
sip_python-0.0.2.dist-info/top_level.txt
sip_python-0.0.2.dist-info/RECORD
sip_python-0.0.2.dist-info/licenses/LICENSE
