Metadata-Version: 2.4
Name: sip_python
Version: 0.0.2
Summary: Python bindings for the SIP solver.
Author-email: João Sousa-Pinto <joaospinto@gmail.com>
Project-URL: Homepage, https://github.com/joaospinto/sip_python
Classifier: Programming Language :: Python :: 3
Classifier: Operating System :: OS Independent
Classifier: Topic :: Scientific/Engineering :: Mathematics
Requires-Python: >=3.10
License-File: LICENSE
Requires-Dist: numpy
Requires-Dist: scipy
Dynamic: license-file
